_version.py
llm_gcp_vertex.py
llm_gcp_vertex-0.2.0.dist-info/METADATA
llm_gcp_vertex-0.2.0.dist-info/WHEEL
llm_gcp_vertex-0.2.0.dist-info/entry_points.txt
llm_gcp_vertex-0.2.0.dist-info/licenses/LICENSE
llm_gcp_vertex-0.2.0.dist-info/RECORD
