Metadata-Version: 2.4
Name: llm-gcp-vertex
Version: 0.2.0
Summary: LLM plugin for Google Cloud Vertex AI models including Gemini and Model Garden
Project-URL: Homepage, https://github.com/ASRagab/llm-gcp-vertex
Project-URL: Repository, https://github.com/ASRagab/llm-gcp-vertex
Author: Ahmad Ragab
License: Apache-2.0
License-File: LICENSE
Keywords: claude,gcp,gemini,google-cloud,llm,model-garden,vertex-ai
Classifier: Development Status :: 4 - Beta
Classifier: Intended Audience :: Developers
Classifier: License :: OSI Approved :: Apache Software License
Classifier: Programming Language :: Python :: 3
Classifier: Programming Language :: Python :: 3.10
Classifier: Programming Language :: Python :: 3.11
Classifier: Programming Language :: Python :: 3.12
Classifier: Programming Language :: Python :: 3.13
Classifier: Programming Language :: Python :: 3.14
Classifier: Topic :: Scientific/Engineering :: Artificial Intelligence
Requires-Python: >=3.10
Requires-Dist: anthropic[vertex]>=0.40.0
Requires-Dist: google-genai>=1.0.0
Requires-Dist: llm>=0.19
Provides-Extra: dev
Requires-Dist: pytest-asyncio>=0.23.0; extra == 'dev'
Requires-Dist: pytest>=8.0.0; extra == 'dev'
